Aquila_Resolve/__init__.py
Aquila_Resolve/__main__.py
Aquila_Resolve/dictionary.py
Aquila_Resolve/filter.py
Aquila_Resolve/format_ph.py
Aquila_Resolve/g2p.py
Aquila_Resolve/h2p.py
Aquila_Resolve/infer.py
Aquila_Resolve/processors.py
Aquila_Resolve/static_dict.py
Aquila_Resolve/symbols.py
Aquila_Resolve/cli/__init__.py
Aquila_Resolve/cli/cli.py
Aquila_Resolve/data/__init__.py
Aquila_Resolve/data/cmudict.json.gz
Aquila_Resolve/data/heteronyms.json
Aquila_Resolve/data/remote.py
Aquila_Resolve/models/__init__.py
Aquila_Resolve/models/dp/__init__.py
Aquila_Resolve/models/dp/phonemizer.py
Aquila_Resolve/models/dp/result.py
Aquila_Resolve/models/dp/model/__init__.py
Aquila_Resolve/models/dp/model/model.py
Aquila_Resolve/models/dp/model/predictor.py
Aquila_Resolve/models/dp/model/utils.py
Aquila_Resolve/models/dp/preprocessing/__init__.py
Aquila_Resolve/models/dp/preprocessing/text.py
Aquila_Resolve/models/dp/preprocessing/utils.py
Aquila_Resolve/text/__init__.py
Aquila_Resolve/text/numbers.py
Aquila_Resolve/text/replace.py
Aquila_Resolve-0.1.4.dist-info/LICENSE
Aquila_Resolve-0.1.4.dist-info/METADATA
Aquila_Resolve-0.1.4.dist-info/WHEEL
Aquila_Resolve-0.1.4.dist-info/entry_points.txt
Aquila_Resolve-0.1.4.dist-info/top_level.txt
Aquila_Resolve-0.1.4.dist-info/RECORD
