Metadata-Version: 2.1
Name: Aquila-Resolve
Version: 0.1.4
Summary: Augmented Neural English G2p converter with Inflectional Orthography.
Home-page: https://github.com/ionite34/Aquila-Resolve
Author: ionite
Author-email: dev@ionite.io
License: Apache 2.0
Classifier: Programming Language :: Python :: 3
Classifier: Programming Language :: Python :: 3 :: Only
Classifier: Programming Language :: Python :: 3.7
Classifier: Programming Language :: Python :: 3.8
Classifier: Programming Language :: Python :: 3.9
Classifier: Programming Language :: Python :: 3.10
Requires-Python: >=3.7
License-File: LICENSE
Requires-Dist: tqdm (>=4.64.0)
Requires-Dist: nltk (>=3.2.5)
Requires-Dist: setuptools (>=57.4.0)
Requires-Dist: pywordsegment (>=0.2.1)
Requires-Dist: torch (<1.13,>=1.11)
Requires-Dist: inflect (>=2.1.0)
Requires-Dist: requests (>=2.23.0)
Requires-Dist: numpy (>=1.18.0)
Requires-Dist: inquirerpy (>=0.3.3)
Requires-Dist: yaspin (>=2.1.0)
Requires-Dist: importlib-resources (~=5.7.1) ; python_version < "3.9"
